hz_scanvirus/GetMD5.py
hz_scanvirus/ListDirectory.py
hz_scanvirus/ScanFile.py
hz_scanvirus/__init__.py
hz_scanvirus/Scan/GetMD5.py
hz_scanvirus/Scan/ListDirectory.py
hz_scanvirus/Scan/ScanFile.py
hz_scanvirus/Scan/__init__.py
hz_scanvirus/Scan/bd/__init__.py
hz_scanvirus-0.5.2.dist-info/LICENSE
hz_scanvirus-0.5.2.dist-info/METADATA
hz_scanvirus-0.5.2.dist-info/WHEEL
hz_scanvirus-0.5.2.dist-info/top_level.txt
hz_scanvirus-0.5.2.dist-info/RECORD
