Metadata-Version: 2.1
Name: hz-scanvirus
Version: 0.5.2
Summary: HeZhong AV Pack. Uses version 5.31 of the engine.
Home-page: https://gitee.com/tjsh/hz_scanvirus
Author: tjsh
Author-email: tjsh.tan@outlook.com
License: UNKNOWN
Platform: UNKNOWN
Classifier: Programming Language :: Python :: 3
Classifier: License :: OSI Approved :: MIT License
Classifier: Operating System :: Microsoft :: Windows
Requires-Python: >=3.6
License-File: LICENSE
